katsuyou/__init__.py
katsuyou/conjugate/__init__.py
katsuyou/conjugate/godan_verb.py
katsuyou/conjugate/i_adjective.py
katsuyou/conjugate/ichidan_verb.py
katsuyou/conjugate/irregular.py
katsuyou/conjugate/util/__init__.py
katsuyou/conjugate/util/bundle.py
katsuyou/util/__init__.py
katsuyou/util/matcher.py
katsuyou-0.1.4.dist-info/METADATA
katsuyou-0.1.4.dist-info/WHEEL
katsuyou-0.1.4.dist-info/top_level.txt
katsuyou-0.1.4.dist-info/RECORD
